import_cmip6_data_utils/download/__init__.py
import_cmip6_data_utils/download/full_catalog.py
import_cmip6_data_utils/download/one_couple.py
import_cmip6_data_utils/download/prepare.py
import_cmip6_data_utils/preprocessing/__init__.py
import_cmip6_data_utils/preprocessing/condense_dictionary.py
import_cmip6_data_utils/preprocessing/reduce_couple_dictionary_keys.py
import_cmip6_data_utils/tools/__init__.py
import_cmip6_data_utils/tools/cmip6_dictionary_keys.py
import_cmip6_data_utils/tools/csv_criteria.py
import_cmip6_data_utils/tools/dataset.py
import_cmip6_data_utils/tools/folders.py
import_cmip6_data_utils/tools/save_and_load_netcdf.py
import_cmip6_data_utils/tools/where_project.py
import_cmip6_data_utils-2025.9.24.dist-info/licenses/LICENSE
import_cmip6_data_utils-2025.9.24.dist-info/METADATA
import_cmip6_data_utils-2025.9.24.dist-info/WHEEL
import_cmip6_data_utils-2025.9.24.dist-info/top_level.txt
import_cmip6_data_utils-2025.9.24.dist-info/RECORD
