Metadata-Version: 2.4
Name: import-cmip6-data-utils
Version: 2025.9.24
Summary: Utilitary package for building notebooks that import CMIP6 data thanks to csv files, based on intake-esgf.
Author-email: Lucas Giboni <lucas.giboni@univ-grenoble-alpes.fr>
License-Expression: BSD-3-Clause
Project-URL: Homepage, https://gricad-gitlab.univ-grenoble-alpes.fr/gibonil/import-cmip6-data-utils
Project-URL: Issues, https://gricad-gitlab.univ-grenoble-alpes.fr/gibonil/import-cmip6-data-utils/-/issues
Keywords: CMIP6,download,data,notebook,utilities,intake-esgf
Classifier: Development Status :: 4 - Beta
Classifier: Operating System :: OS Independent
Classifier: Programming Language :: Python :: 3
Classifier: Programming Language :: Python :: 3.10
Classifier: Programming Language :: Python :: 3.11
Classifier: Programming Language :: Python :: 3.12
Classifier: Programming Language :: Python :: 3.13
Classifier: Intended Audience :: Science/Research
Classifier: Topic :: Scientific/Engineering
Requires-Python: >=3.10
License-File: LICENSE
Requires-Dist: intake-esgf
Requires-Dist: ipykernel
Requires-Dist: ipywidgets
Requires-Dist: pandas
Requires-Dist: xarray
Requires-Dist: xcdat
Requires-Dist: tabulate
Provides-Extra: dev
Requires-Dist: pytest; extra == "dev"
Dynamic: license-file
